onshapy/__init__.py
onshapy/api.py
onshapy/models/__init__.py
onshapy/models/document.py
onshapy/models/element.py
onshapy/models/modelbase.py
onshapy/models/part.py
onshapy/models/workspace.py
onshapy/stl.py
onshapy/urlinfo.py
onshapy-0.3.2.dist-info/LICENSE
onshapy-0.3.2.dist-info/METADATA
onshapy-0.3.2.dist-info/WHEEL
onshapy-0.3.2.dist-info/RECORD
